lib/liblaszip_base.a
lib/liblaszip_base_api.a
laszip-0.2.4.dist-info/WHEEL
laszip-0.2.4.dist-info/METADATA
laszip-0.2.4.dist-info/RECORD
laszip-0.2.4.dist-info/licenses/License.txt
include/laszip/laszip_api_version.h
include/laszip/laszip_api.h
laszip/__init__.py
laszip/laszip.cpython-310-aarch64-linux-gnu.so
