Metadata-Version: 2.2
Name: laszip
Version: 0.2.4
Summary: Bindings for LASzip made with pybind11
Author-Email: Thomas Montaigu <thomas.montaigu@laposte.net>
License: MIT License
Project-URL: repository, https://github.com/tmontaigu/laszip-python
Requires-Python: >=3.9
